binoculars/__init__.py
binoculars-0.1.3.dist-info/LICENSE
binoculars-0.1.3.dist-info/METADATA
binoculars-0.1.3.dist-info/WHEEL
binoculars-0.1.3.dist-info/top_level.txt
binoculars-0.1.3.dist-info/RECORD
