Metadata-Version: 2.1
Name: binoculars
Version: 0.1.3
Summary: Various calculations for binomial confidence intervals.
Home-page: https://github.com/nolanbconaway/binoculars
Author: Nolan Conaway
Author-email: nolanbconaway@gmail.com
License: MIT
Keywords: statistics,binomial,confidence
Platform: UNKNOWN
Classifier: Programming Language :: Python :: 3.6
Classifier: Programming Language :: Python :: 3.7
Classifier: Programming Language :: Python :: 3.8
Requires-Dist: scipy
Requires-Dist: numpy
Provides-Extra: test
Requires-Dist: black (==20.8b1) ; extra == 'test'
Requires-Dist: pytest (==6.2.1) ; extra == 'test'
Requires-Dist: pytest-cov (==2.10.1) ; extra == 'test'
Requires-Dist: codecov (==2.1.11) ; extra == 'test'
